CHANGELOG.txt
LICENCE.txt
MANIFEST.in
README.txt
Usage.txt
setup.py
petrabytesunitconverter/__init__.py
petrabytesunitconverter.egg-info/PKG-INFO
petrabytesunitconverter.egg-info/SOURCES.txt
petrabytesunitconverter.egg-info/dependency_links.txt
petrabytesunitconverter.egg-info/requires.txt
petrabytesunitconverter.egg-info/top_level.txt