Metadata-Version: 1.1
Name: petrabytesunitconverter
Version: 0.0.2
Summary: Can convert scientific units.
Home-page: https://www.petrabytes.com/
Author: Lalan Ranjan
Author-email: lranjan@petrabytes.com
License: Petrabytes Corp.
Keywords: Unit_Converter
Platform: UNKNOWN
Classifier: Development Status :: 5 - Production/Stable
Classifier: Intended Audience :: Developers
Classifier: Operating System :: OS Independent
Classifier: License :: OSI Approved :: Open Software License 3.0 (OSL-3.0) 
Classifier: Programming Language :: Python :: 3
Classifier: Programming Language :: Python :: 3.6
Classifier: Programming Language :: Python :: 3.7
Classifier: Programming Language :: Python :: 3.8
